anomeda/DataFrame.py
anomeda/__init__.py
anomeda/utils.py
anomeda-0.1.4.dist-info/LICENSE
anomeda-0.1.4.dist-info/METADATA
anomeda-0.1.4.dist-info/WHEEL
anomeda-0.1.4.dist-info/top_level.txt
anomeda-0.1.4.dist-info/RECORD
